pymatgen/io/fleur/__init__.py
pymatgen/io/fleur/fleurinput.py
pymatgen/io/fleur/tests/test_fleurinput.py
pymatgen_io_fleur-0.5.0.dist-info/LICENSE
pymatgen_io_fleur-0.5.0.dist-info/WHEEL
pymatgen_io_fleur-0.5.0.dist-info/METADATA
pymatgen_io_fleur-0.5.0.dist-info/RECORD
