Metadata-Version: 2.1
Name: pymatgen-io-fleur
Version: 0.5.0
Summary: A pymatgen add-on for IO for the fleur code.
Keywords: pymatgen,fleur
Author-email: The JuDFT team <he.janssen@fz-juelich.de>
Requires-Python: >=3.8
Classifier: Programming Language :: Python :: 3
Classifier: Programming Language :: Python :: 3.8
Classifier: Programming Language :: Python :: 3.9
Classifier: Programming Language :: Python :: 3.10
Classifier: Programming Language :: Python :: 3.11
Classifier: Development Status :: 4 - Beta
Classifier: Intended Audience :: Science/Research
Classifier: License :: OSI Approved :: MIT License
Classifier: Operating System :: OS Independent
Classifier: Topic :: Scientific/Engineering :: Information Analysis
Classifier: Topic :: Scientific/Engineering :: Physics
Classifier: Topic :: Scientific/Engineering :: Chemistry
Classifier: Topic :: Software Development :: Libraries :: Python Modules
Requires-Dist: pymatgen>=2022.7.8
Requires-Dist: masci-tools>=0.13
Requires-Dist: pre-commit>=2.6.0 ; extra == "pre-commit"
Requires-Dist: pylint~=2.12.2 ; extra == "pre-commit"
Requires-Dist: pytest~=6.0 ; extra == "testing"
Requires-Dist: pytest-cov~=3.0 ; extra == "testing"
Project-URL: Home, https://github.com/JuDFTteam/pymatgen-io-fleur
Project-URL: Source, https://github.com/JuDFTteam/pymatgen-io-fleur
Provides-Extra: pre-commit
Provides-Extra: testing
